pyelf/__init__.py
pyelf/cli.py
pyelf/pyelf.py
sauci_pyelf-0.1.2.dist-info/LICENSE
sauci_pyelf-0.1.2.dist-info/METADATA
sauci_pyelf-0.1.2.dist-info/WHEEL
sauci_pyelf-0.1.2.dist-info/entry_points.txt
sauci_pyelf-0.1.2.dist-info/top_level.txt
sauci_pyelf-0.1.2.dist-info/RECORD
