Metadata-Version: 2.1
Name: sauci-pyelf
Version: 0.1.2
Summary: high level API to retrieve information from ELF files.
Home-page: https://github.com/Sauci/pyelf
Author: Guillaume Sottas
Author-email: guillaumesottas@gmail.com
License: MIT
Project-URL: Bug Tracker, https://github.com/Sauci/pyelf/issues
Platform: UNKNOWN
Classifier: License :: OSI Approved :: MIT License
Requires-Python: >=2.7.14
License-File: LICENSE
Requires-Dist: pyelftools
